{
    "a_name": "exp_38",
    "a_description": "Final version, convnext base, img size 384",
    "type": "TEACHER",
    "batch_size": 8,
    "image_size": 384,
    "num_workers": 4,
    "n_frames": 1,
    "n_eval": 5,
    "accumulation_steps": 4,
    "smoothing_value": 0.1,
    "n_mul_dataset": 1,
    "use_mixup": true,
    "use_cutmix": false,
    "use_gridmask": false,
    "use_cutout": true,
    "use_arcface": false,
    "use_TTA": false,
    "use_random_augment": false,
    "only_augment_real": false,
    "use_random_resize_crop": true,
    "use_hsv": false,
    "model_ema_decay": 0.99,
    "start_ema_epoch": 0,
    "crop_face": false,
    "pseudo_label": false,
    "lr": 0.00017015324133333334,
    "num_epoch": 120,
    "weight_decay": 0.02,
    "mixup_alpha": 0.7,
    "arcface_m": 0.5,
    "arcface_s": 80,
    "backbone": "convnext_base_384_in22ft1k",
    "optimizer": "ADAN"
  }